LICENSE
MANIFEST.in
README.md
setup.py
./src/pijavski.cpp
dist/pijavski-0.0.6-cp38-cp38-linux_x86_64.whl
dist/pijavski-0.0.6.tar.gz
src/cdefs.h
src/heap.h
src/pij_build.py
src/pijavski.h
src/pijavski.py
src/pijavski.egg-info/PKG-INFO
src/pijavski.egg-info/SOURCES.txt
src/pijavski.egg-info/dependency_links.txt
src/pijavski.egg-info/requires.txt
src/pijavski.egg-info/top_level.txt