Metadata-Version: 2.1
Name: pijavski
Version: 0.0.6
Summary: Python CFFI bindings for Pijavski C++ function to calculate minimum of a given function.
Home-page: UNKNOWN
Author: Santiago Velasquez
Author-email: js.velasquez123@gmail.com
License: UNKNOWN
Platform: UNKNOWN
Classifier: Programming Language :: Python :: 2
Classifier: Programming Language :: Python :: 3
Classifier: License :: OSI Approved :: GNU General Public License v3 (GPLv3)
